phylo2vec/__init__.py
phylo2vec/_phylo2vec_core.abi3.so
phylo2vec/base/__init__.py
phylo2vec/base/ancestry.py
phylo2vec/base/edges.py
phylo2vec/base/newick.py
phylo2vec/base/pairs.py
phylo2vec/cli.py
phylo2vec/datasets/__init__.py
phylo2vec/datasets/_base.py
phylo2vec/datasets/data/__init__.py
phylo2vec/datasets/descr/__init__.py
phylo2vec/datasets/descr/fluA.md
phylo2vec/datasets/descr/h3n2.md
phylo2vec/datasets/descr/m501.md
phylo2vec/datasets/descr/yeast.md
phylo2vec/datasets/descr/zika.md
phylo2vec/io/__init__.py
phylo2vec/io/_validation.py
phylo2vec/io/reader.py
phylo2vec/io/writer.py
phylo2vec/metrics.py
phylo2vec/opt/README.md
phylo2vec/opt/__init__.py
phylo2vec/opt/_api.py
phylo2vec/opt/_base.py
phylo2vec/opt/_beagle_losses.py
phylo2vec/opt/_gradme.py
phylo2vec/opt/_gradme_losses.py
phylo2vec/opt/_hc.py
phylo2vec/opt/_hc_losses.py
phylo2vec/opt/utils.py
phylo2vec/stats/__init__.py
phylo2vec/stats/nodewise.py
phylo2vec/stats/treewise.py
phylo2vec/utils/__init__.py
phylo2vec/utils/matrix.py
phylo2vec/utils/newick.py
phylo2vec/utils/vector.py
phylo2vec-1.7.0.dist-info/METADATA
phylo2vec-1.7.0.dist-info/WHEEL
phylo2vec-1.7.0.dist-info/entry_points.txt
phylo2vec-1.7.0.dist-info/licenses/LICENSE
phylo2vec.libs/libgcc_s-9d28dc04.so.1
phylo2vec-1.7.0.dist-info/RECORD
