Metadata-Version: 2.4
Name: phylo2vec
Version: 1.7.0
Classifier: Development Status :: 3 - Alpha
Classifier: Topic :: Scientific/Engineering :: Bio-Informatics
Classifier: Programming Language :: Python
Classifier: Programming Language :: Python :: 3
Classifier: Programming Language :: Python :: 3.10
Classifier: Programming Language :: Python :: 3.11
Classifier: Programming Language :: Python :: 3.12
Classifier: Programming Language :: Python :: 3.13
Classifier: License :: OSI Approved :: GNU Lesser General Public License v3 (LGPLv3)
Classifier: Operating System :: Unix
Classifier: Operating System :: Microsoft :: Windows
Requires-Dist: numpy>=1.22,<2.3
Requires-Dist: biopython>=1.84.0
Requires-Dist: joblib>=1.2.0
Requires-Dist: ete4==4.4.0
Requires-Dist: six>=1.16.0
Requires-Dist: jax ; extra == 'opt'
Requires-Dist: joblib ; extra == 'opt'
Requires-Dist: optax ; extra == 'opt'
Requires-Dist: rpy2 ; extra == 'opt'
Requires-Dist: tqdm ; extra == 'opt'
Provides-Extra: opt
License-File: LICENSE
Summary: Phylo2Vec: integer vector representation of binary (phylogenetic) trees
Author-email: Neil Scheidwasser <neil.clow@sund.ku.dk>
Requires-Python: >=3.10, <=3.13
